mlflow/__init__.py
mlflow/server/js/build/asset-manifest.json
mlflow/server/js/build/favicon.ico
mlflow/server/js/build/index.html
mlflow/server/js/build/manifest.json
mlflow/server/js/build/pdf.worker.js
mlflow/server/js/build/lib/ml-model-trace-renderer/index.html
mlflow/server/js/build/lib/ml-model-trace-renderer/css/967.b6918afe.chunk.css
mlflow/server/js/build/lib/ml-model-trace-renderer/js/180.869b170a.chunk.js
mlflow/server/js/build/lib/ml-model-trace-renderer/js/199.7e242aee.chunk.js
mlflow/server/js/build/lib/ml-model-trace-renderer/js/2.50231fdd.chunk.js
mlflow/server/js/build/lib/ml-model-trace-renderer/js/214.13558a5b.chunk.js
mlflow/server/js/build/lib/ml-model-trace-renderer/js/35.1623fe90.chunk.js
mlflow/server/js/build/lib/ml-model-trace-renderer/js/381.b0dd6b18.chunk.js
mlflow/server/js/build/lib/ml-model-trace-renderer/js/487.9372e2e0.chunk.js
mlflow/server/js/build/lib/ml-model-trace-renderer/js/541.b181f44e.chunk.js
mlflow/server/js/build/lib/ml-model-trace-renderer/js/799.26151587.chunk.js
mlflow/server/js/build/lib/ml-model-trace-renderer/js/939.91d5961d.chunk.js
mlflow/server/js/build/lib/ml-model-trace-renderer/js/967.92e18d95.chunk.js
mlflow/server/js/build/lib/ml-model-trace-renderer/js/ml-model-trace-renderer.417506a1.js
mlflow/server/js/build/lib/notebook-trace-renderer/index.html
mlflow/server/js/build/lib/notebook-trace-renderer/css/967.b6918afe.chunk.css
mlflow/server/js/build/lib/notebook-trace-renderer/js/180.869b170a.chunk.js
mlflow/server/js/build/lib/notebook-trace-renderer/js/199.7e242aee.chunk.js
mlflow/server/js/build/lib/notebook-trace-renderer/js/2.50231fdd.chunk.js
mlflow/server/js/build/lib/notebook-trace-renderer/js/214.13558a5b.chunk.js
mlflow/server/js/build/lib/notebook-trace-renderer/js/427.e0f9eac2.chunk.js
mlflow/server/js/build/lib/notebook-trace-renderer/js/541.b181f44e.chunk.js
mlflow/server/js/build/lib/notebook-trace-renderer/js/713.2eb30324.chunk.js
dataflow_mlflow-0.0.1.dist-info/METADATA
dataflow_mlflow-0.0.1.dist-info/WHEEL
dataflow_mlflow-0.0.1.dist-info/top_level.txt
dataflow_mlflow-0.0.1.dist-info/RECORD
