Metadata-Version: 2.4
Name: dataflow-mlflow
Version: 0.0.1
Summary: MLflow customized for Dataflow
Home-page: https://github.com/Digital-Back-Office/dataflow-mlflow
Author: Dataflow
Requires-Dist: mlflow==3.1.1
Dynamic: author
Dynamic: home-page
Dynamic: requires-dist
Dynamic: summary
